fastapi_components/__init__.py
fastapi_components/components/__init__.py
fastapi_components/components/base.py
fastapi_components/components/http_session.py
fastapi_components/components/kafka_producer.py
fastapi_components/components/mongo.py
fastapi_components/components/postgres.py
fastapi_components/components/py.typed
fastapi_components/components/redis.py
fastapi_components/lifecycle.py
fastapi_components/logging.py
fastapi_components/py.typed
fastapi_components/state.py
fastapi_components/state_manager.py
fastapi_components-0.4.1.dist-info/LICENSE
fastapi_components-0.4.1.dist-info/WHEEL
fastapi_components-0.4.1.dist-info/METADATA
fastapi_components-0.4.1.dist-info/RECORD
